cxpm/__init__.py
cxpm/__main__.py
cxpm/cmake.py
cxpm/config.ini
cxpm/config.py
cxpm/git.py
cxpm/shell.py
cxpm/tools.py
cxpm-0.0.1.dist-info/METADATA
cxpm-0.0.1.dist-info/WHEEL
cxpm-0.0.1.dist-info/entry_points.txt
cxpm-0.0.1.dist-info/licenses/LICENSE
cxpm-0.0.1.dist-info/RECORD
