Metadata-Version: 2.1
Name: cxpm
Version: 0.0.1
Summary: a package manager
Project-URL: Homepage, https://github.com/cxproj/cxpm
Project-URL: Documentation, https://github.com/cxproj/cxpm
Project-URL: Repository, https://github.com/cxproj/cxpm.git
Project-URL: Issues, https://github.com/cxproj/cxpm/issues
Author-email: Wei Caixin <weicaixin@qq.com>
License: MIT License
License-File: LICENSE
Keywords: cxpm
Classifier: Development Status :: 4 - Beta
Classifier: Programming Language :: Python
Requires-Python: >=3.8
